[
        {
                "id":"gold",
                "name":"junk",
                "desc":"Gold Coins",
                "locked":false,
                "max":5
        },
        {
                "id":"suit",
                "desc":"Integrity of your space suit",
                "locked":false,
                "hidden":true,
                "value":1,
                "max":5
        },
        {
                "id":"research",
                "desc":"Research into the technical",
                "max":10
        },
        {
                "id":"arcana",
                "school":"arcane",
                "desc":"Profound mystical knowledge",
                "max":0
        },
        {
                "id":"scrap",
                "desc":"miscellaneous objects of dubious use",
                "max":10
        },
        {       "id":"datasource",
                "name":"Data source",
                "desc":"May contain useful information",
                "max":10,
                "mod":{
                        "research.rate":0.005,
                        "research.max":1
                }
         },
         {
                "id":"medicaldata",
                "name":"medical data",
                "max":20,
                "mod":{
                        "biology.max":0.05
                }
        },
        {
                "id":"medicalsupplies",
                "name":"medical supplies",
                "max":20
        },
                 {
                "id":"electronics",
                "desc":"robot bones.",
                "max":10
        },
        {
                "id":"processing",
                "desc":"Processing power",
                "max":10
        },
        {
                "id":"smallbatteries",
                "name":"Small batteries",
                "desc":"Powers your small devices",
                "max":1
        },
        {
                "id":"space",
                "name":"floor space",
                "desc":"Space Available",
                "reverse":true,
                "max":0
        },
        {
                "id":"mana",
                "tags":"manas",
                "desc":"raw magical energy",
                "unit":false,
                "name":"mana",
                "max":5
        },
        {
                "id":"fire",
                "unit":false,
                "tags":"manas,element",
                "desc":"Fire Mana",
                "max":0
        },
        {
                "id":"air",
                "unit":false,
                "tags":"manas,element",
                "desc":"Air Mana",
                "max":0
        },
        {
                "id":"earth",
                "unit":false,
                "tags":"manas,element",
                "desc":"Earth Mana",
                "max":0
        },
        {
                "id":"water",
                "unit":false,
                "tags":"manas,element",
                "desc":"Water Mana",
                "max":0
        },
        {
                "id":"nature",
                "tags":"manas",
                "unit":false,
                "desc":"Nature Mana",
                "max":0
        },
        {
                "id":"shadow",
                "name":"shadow",
                "tags":"manas",
                "unit":false,
                "desc":"Shadow mana",
                "max":0
        },
        {
                "id":"light",
                "tags":"manas",
                "unit":false,
                "desc":"Light mana",
                "max":0
        },
        {


                "id":"spirit",
                "tags":"manas",
                "unit":false,
                "desc":"Spirit mana",
                "max":0
        },
        {
                "id":"tempus",
                "tags":"manas",
                "unit":false,
                "desc":"Time incarnate. If only...",
                "max":0
        },
        {
                "id":"chaos",
                "tags":"manas",
                "unit":false,
                "desc":"Chaos incarnate. No current use.",
                "max":0
        },
        {
                "id":"void",
                "tags":"manas",
                "unit":false,
                "desc":"nothingness. No current use.",
                "flavor":"",
                "max":0
        }


]
